n8loom/__init__.py
n8loom/cache_utils.py
n8loom/loom.py
n8loom/sample_utils.py
n8loom/utils.py
n8loom/examples/__init__.py
n8loom/examples/reflection.py
n8loom/examples/server.py
n8loom-0.1.2.dist-info/LICENSE
n8loom-0.1.2.dist-info/METADATA
n8loom-0.1.2.dist-info/WHEEL
n8loom-0.1.2.dist-info/top_level.txt
n8loom-0.1.2.dist-info/RECORD
