Metadata-Version: 2.2
Name: n8loom
Version: 0.1.2
License-File: LICENSE
Requires-Dist: annotated-types==0.7.0
Requires-Dist: anyio==4.8.0
Requires-Dist: certifi==2025.1.31
Requires-Dist: charset-normalizer==3.4.1
Requires-Dist: click==8.1.8
Requires-Dist: exceptiongroup==1.2.2
Requires-Dist: fastapi==0.115.8
Requires-Dist: filelock==3.17.0
Requires-Dist: fsspec==2025.2.0
Requires-Dist: h11==0.14.0
Requires-Dist: huggingface-hub==0.28.1
Requires-Dist: idna==3.10
Requires-Dist: Jinja2==3.1.5
Requires-Dist: MarkupSafe==3.0.2
Requires-Dist: mlx==0.22.0
Requires-Dist: mlx-lm==0.21.1
Requires-Dist: numpy==2.2.2
Requires-Dist: packaging==24.2
Requires-Dist: protobuf==5.29.3
Requires-Dist: pydantic==2.10.6
Requires-Dist: pydantic_core==2.27.2
Requires-Dist: PyYAML==6.0.2
Requires-Dist: regex==2024.11.6
Requires-Dist: requests==2.32.3
Requires-Dist: safetensors==0.5.2
Requires-Dist: sentencepiece==0.2.0
Requires-Dist: setuptools==75.8.0
Requires-Dist: sniffio==1.3.1
Requires-Dist: starlette==0.45.3
Requires-Dist: tokenizers==0.21.0
Requires-Dist: tqdm==4.67.1
Requires-Dist: transformers==4.48.2
Requires-Dist: typing_extensions==4.12.2
Requires-Dist: urllib3==2.3.0
Requires-Dist: uvicorn==0.34.0
